pyfwfinder/__init__.py
pyfwfinder/py.typed
pyfwfinder/pyfwfinder.cpython-310-x86_64-linux-gnu.so
pyfwfinder/pyfwfinder.pyi
pyfwfinder.libs/libudev-f937d4f9.so.1.7.5
pyfwfinder-0.4.2.dist-info/METADATA
pyfwfinder-0.4.2.dist-info/WHEEL
pyfwfinder-0.4.2.dist-info/RECORD
