Metadata-Version: 2.1
Name: pyfwfinder
Version: 0.4.2
Summary: Python API to find Free-WiLi devices
Author-Email: David Rebbe <drebbe@intrepidcs.com>
Classifier: License :: OSI Approved :: MIT License
Project-URL: Homepage, https://github.com/freewili/freewili-finder
Requires-Python: >=3.8
